rx/__init__.py
rx/py.typed
rx/core/__init__.py
rx/core/notification.py
rx/core/pipe.py
rx/core/run.py
rx/core/typing.py
rx/core/abc/__init__.py
rx/core/abc/asyncobservable.py
rx/core/abc/asyncobserver.py
rx/core/abc/disposable.py
rx/core/abc/observable.py
rx/core/abc/observer.py
rx/core/abc/periodicscheduler.py
rx/core/abc/scheduler.py
rx/core/abc/startable.py
rx/core/abc/subject.py
rx/core/observable/__init__.py
rx/core/observable/amb.py
rx/core/observable/case.py
rx/core/observable/catch.py
rx/core/observable/combinelatest.py
rx/core/observable/concat.py
rx/core/observable/connectableobservable.py
rx/core/observable/defer.py
rx/core/observable/empty.py
rx/core/observable/fromcallback.py
rx/core/observable/fromfuture.py
rx/core/observable/fromiterable.py
rx/core/observable/generate.py
rx/core/observable/generatewithrelativetime.py
rx/core/observable/groupedobservable.py
rx/core/observable/ifthen.py
rx/core/observable/interval.py
rx/core/observable/marbles.py
rx/core/observable/merge.py
rx/core/observable/never.py
rx/core/observable/observable.py
rx/core/observable/onerrorresumenext.py
rx/core/observable/range.py
rx/core/observable/repeat.py
rx/core/observable/returnvalue.py
rx/core/observable/start.py
rx/core/observable/startasync.py
rx/core/observable/throw.py
rx/core/observable/timer.py
rx/core/observable/toasync.py
rx/core/observable/using.py
rx/core/observable/withlatestfrom.py
rx/core/observable/zip.py
rx/core/observer/__init__.py
rx/core/observer/autodetachobserver.py
rx/core/observer/observeonobserver.py
rx/core/observer/observer.py
rx/core/observer/scheduledobserver.py
rx/core/operators/__init__.py
rx/core/operators/all.py
rx/core/operators/amb.py
rx/core/operators/asobservable.py
rx/core/operators/average.py
rx/core/operators/buffer.py
rx/core/operators/bufferwithtime.py
rx/core/operators/bufferwithtimeorcount.py
rx/core/operators/catch.py
rx/core/operators/combinelatest.py
rx/core/operators/concat.py
rx/core/operators/contains.py
Rx-3.0.1.dist-info/LICENSE
Rx-3.0.1.dist-info/METADATA
Rx-3.0.1.dist-info/WHEEL
Rx-3.0.1.dist-info/top_level.txt
Rx-3.0.1.dist-info/zip-safe
Rx-3.0.1.dist-info/RECORD
