Metadata-Version: 1.2
Name: Rx
Version: 3.0.1
Summary: Reactive Extensions (Rx) for Python
Home-page: http://reactivex.io
Author: Dag Brattli
Author-email: dag@brattli.net
License: MIT License
Download-URL: https://github.com/ReactiveX/RxPY
Platform: UNKNOWN
Classifier: Development Status :: 5 - Production/Stable
Classifier: Environment :: Other Environment
Classifier: Intended Audience :: Developers
Classifier: License :: OSI Approved :: MIT License
Classifier: Operating System :: OS Independent
Classifier: Programming Language :: Python :: 3
Classifier: Programming Language :: Python :: 3.6
Classifier: Programming Language :: Python :: 3.7
Classifier: Programming Language :: Python :: Implementation :: CPython
Classifier: Topic :: Software Development :: Libraries :: Python Modules
Requires-Python: >=3.6.0
